{
	"$schema": "https://raw.githubusercontent.com/totvs/ttalk-standard-message/master/jsonschema/schemas/ArmazenagemCargaNaoDesunitizada_2_69690.json#",
	"info": {
		"description": "Contrato de Mensagem Padronizada para a entidade filial (Branch) para produtos TOTVS",
		"version": "2.001",
		"title": "Branch",
		"contact": {
			"name": "T-Talk",
			"url": "API.Totvs.com.br",
			"email": "comiteintegracao@totvs.com.br"
		},
		"x-totvs": {
			"messageDocumentation": {
				"name": "Consulta RFB",
				"description": "Joinville",
				"segment": "Logística"
			},
			"productInformation": [
				{
					"product": "sara",
					"contact": "SUPPLY.ML.LOG.SARA-SIP@totvs.com.br",
					"description": "Consulta RFB - Armazenagem de Carga não Desunitizada",
					"adapter": "proc_rfb_1_5.sql",
					"helpUrl": "tdn.totvs.com/pages/viewpage.action?pageId=???"
				}
			]
		}
	},
	"definitions": {
		"RegistroCargaNaoDesunitizada": {
			"type": "object",
			"allOf": [
				{
					"$ref": "https://raw.githubusercontent.com/totvs/ttalk-standard-message/master/jsonschema/apis/types/totvsApiTypesBase.json#/definitions/Paging"
				},
				{
					"type": "object",
					"properties": {
						"items": {
							"type": "array",
							"items": {
								"$ref": "#/definitions/CargaNaoDesunitizada"
							}
						}
					}
				}
			]
		},
		"RegistroCargaNaoDesunitizadaXls": {
			"type": "object",
			"properties": {
				"fileName": {
					"type": "string",
					"example": "www.totvs.com.br/sara/arquivos/arquivo_001.xls",
					"description": "Arquivo XLS"
				}
			}
		},
		"CargaNaoDesunitizada": {
			"type": "object",
			"properties": {
				"TipoConhecimento": {
					"type": "string",
					"example": "BL",
					"description": "Tipo de Conhecimento do Lote",
					"x-totvs": [
						{
							"product": "sara",
							"Field": "conhec_nome",
							"Required": true,
							"type": "varchar",
							"length": "100",
							"available": true,
							"canUpdate": false
						}
					]
				},
				"NumeroDocTransporte": {
					"type": "string",
					"example": "2015/000000151-000001",
					"description": "Número do Conhecimento do Lote",
					"x-totvs": [
						{
							"product": "sara",
							"Field": "num_doc_transp",
							"Required": true,
							"type": "varchar",
							"length": "100",
							"available": true,
							"canUpdate": false
						}
					]
				},
				"idLoteCarga": {
					"type": "string",
					"example": "15/000008-4",
					"description": "Número do Lote de Carga",
					"x-totvs": [
						{
							"product": "sara",
							"Field": "latu_lote",
							"Required": true,
							"type": "varchar",
							"length": "100",
							"available": true,
							"canUpdate": false
						}
					]
				},
				"TipoCarga": {
					"type": "string",
					"example": "Outros",
					"description": "Natureza da Carga",
					"x-totvs": [
						{
							"product": "sara",
							"Field": "tipo_carga",
							"Required": true,
							"type": "varchar",
							"length": "100",
							"available": true,
							"canUpdate": false
						}
					]
				},
				"NomeEspecie": {
					"type": "string",
					"example": "Bobina",
					"description": "Nome da Espécie da Mercadoria",
					"x-totvs": [
						{
							"product": "sara",
							"Field": "esp_descricao",
							"Required": true,
							"type": "varchar",
							"length": "100",
							"available": true,
							"canUpdate": false
						}
					]
				},
				"NumeroUnidadeCarga": {
					"type": "string",
					"example": "TTNU6546548",
					"description": "Número da unidade de carga - contêiner",
					"x-totvs": [
						{
							"product": "sara",
							"Field": "numero_unidade",
							"Required": true,
							"type": "varchar",
							"length": "100",
							"available": true,
							"canUpdate": false
						}
					]
				},
				"NomeAreaArmazenagem": {
					"type": "string",
					"example": "PATIO A - CARGA GERAL",
					"description": "Nome da área onde está localizado a carga armazenada.",
					"x-totvs": [
						{
							"product": "sara",
							"Field": "arm_descricao",
							"Required": true,
							"type": "varchar",
							"length": "100",
							"available": true,
							"canUpdate": false
						}
					]
				},
				"QuadraAreaArmazenagem": {
					"type": "string",
					"example": "00007",
					"description": "Quadra onde está localizado a carga armazenada.",
					"x-totvs": [
						{
							"product": "sara",
							"Field": "cel_quadra",
							"Required": true,
							"type": "varchar",
							"length": "100",
							"available": true,
							"canUpdate": false
						}
					]
				},
				"RuaAreaArmazenagem": {
					"type": "string",
					"example": "00001",
					"description": "Informação da rua onde está localizada a carga armazenada.",
					"x-totvs": [
						{
							"product": "sara",
							"Field": "cel_rua",
							"Required": true,
							"type": "varchar",
							"length": "100",
							"available": true,
							"canUpdate": false
						}
					]
				},
				"BlocoAreaArmazenagem": {
					"type": "string",
					"example": "00001",
					"description": "Bloco onde está localizada a carga armazenada.",
					"x-totvs": [
						{
							"product": "sara",
							"Field": "cel_bloco",
							"Required": true,
							"type": "varchar",
							"length": "100",
							"available": true,
							"canUpdate": false
						}
					]
				},
				"PrateleiraAreaArmazenagem": {
					"type": "string",
					"example": "00001",
					"description": "Prateleira onde está localizado a carga armazenada.",
					"x-totvs": [
						{
							"product": "sara",
							"Field": "cel_prateleira",
							"Required": true,
							"type": "varchar",
							"length": "100",
							"available": true,
							"canUpdate": false
						}
					]
				},
				"NivelAreaArmazenagem": {
					"type": "string",
					"example": "00002",
					"description": "Nível da localização da carga armazenada.",
					"x-totvs": [
						{
							"product": "sara",
							"Field": "cel_nivel",
							"Required": true,
							"type": "varchar",
							"length": "100",
							"available": true,
							"canUpdate": false
						}
					]
				},
				"PosicaoAreaArmazenagem": {
					"type": "string",
					"example": "00001",
					"description": "Posição onde está localizado a carga armazenada.",
					"x-totvs": [
						{
							"product": "sara",
							"Field": "cel_posicao",
							"Required": true,
							"type": "varchar",
							"length": "100",
							"available": true,
							"canUpdate": false
						}
					]
				},
				"AlturaAreaArmazenazem": {
					"type": "string",
					"example": "50",
					"description": "Altura (nível), localização de carga não desunitizada (coordenadas).",
					"x-totvs": [
						{
							"product": "sara",
							"Field": "tiso_altura",
							"Required": true,
							"type": "varchar",
							"length": "100",
							"available": true,
							"canUpdate": false
						}
					]
				},
				"LarguraAreaArmazenagem": {
					"type": "string",
					"example": "100",
					"description": "Largura (profundidade), localização de carga não desunitizada (coordenadas).",
					"x-totvs": [
						{
							"product": "sara",
							"Field": "tiso_largura",
							"Required": true,
							"type": "varchar",
							"length": "100",
							"available": true,
							"canUpdate": false
						}
					]
				},
				"ComprimentoAreaArmazenagem": {
					"type": "string",
					"example": "1000",
					"description": "Comprimento (frente), localização de carga não desunitizada (coordenadas).",
					"x-totvs": [
						{
							"product": "sara",
							"Field": "tiso_comprimento",
							"Required": true,
							"type": "varchar",
							"length": "100",
							"available": true,
							"canUpdate": false
						}
					]
				}
			}
		}
	}
}