{
	"$schema": "https://raw.githubusercontent.com/totvs/ttalk-standard-message/master/jsonschema/schemas/ProductionAppointment_2_003.json#",
	"info": {
		"description": "",
		"version": "2.003",
		"title": "ProductionAppointment",
		"contact": {},
		"x-totvs": {
			"messageDocumentation": {
				"name": "ProductionAppointment",
				"description": "Apontamento de produção (incluindo MOB/GGF)",
				"segment": ""
			},
			"productInformation": [
				{
					"product": "DATASUL",
					"contact": "André Luís Oliveira Pereira",
					"note": "",
					"adapter": ""
				}
			],
			"transactionDefinition": {
				"subType": "event",
				"businessContentType": {
					"$ref": "#/definitions/BusinessContentType",
					"type": "object"
				},
				"returnContentType": {
					"$ref": "#/definitions/ReturnContentType",
					"type": "object"
				}
			}
		}
	},
	"definitions": {
		"BusinessContentType": {
			"type": "object",
			"properties": {
				"MachineCode": {
					"description": "Código Máquina",
					"type": "string",
					"maxLength": 20,
					"x-totvs": [
						{
							"product": "Protheus",
							"field": "SH6.H6_RECURSO/CYV.CYV_CDMQ",
							"note" : "O campo SH6.H6_RECURSO é utilizado no Protheus PCP e o campo CYV.CYV_CDMQ é utilizado no Protheus SFC",
							"required": false,
							"available": true
						},
						{
							"product": "Logix",
							"field": "man_apo_detalhe.eqpto",
							"required": false,
							"available": true
						},
						{
							"product": "Datasul ",
							"field": "rep-oper-ctrab.cod-ctrab",
							"required": false,
							"available": true
						}

					]
				},
				"MachineDescription": {
					"description": "Descrição Máquina",
					"type": "string",
					"maxLength": 40
				},
				"ProductionOrderNumber": {
					"description": "Número Ordem Produção",
					"type": "string",
					"maxLength": 20,
					"x-totvs": [
						{
							"product": "Protheus",
							"field": "SH6.H6_OP/CYV.CYV_NRORPO",
							"note" : "O campo SH6.H6_OP é utilizado no Protheus PCP e o campo CYV.CYV_NRORPO é utilizado no Protheus SFC",
							"required": false,
							"available": true
						},
						{
							"product": "Logix",
							"field": "man_apo_mestre.ordem_producao",
							"required": false,
							"available": true
						},
						{
							"product": "Datasul ",
							"field": "rep-prod.nr-ord-prod",
							"required": false,
							"available": true
						}

					]
				},
				"ActivityID": {
					"description": "ID Operação",
					"type": "string",
					"maxLength": 10,
					"x-totvs": [
						{
							"product": "Protheus",
							"field": "SH6.H6_OP/CYV.CYV_NRORPO",
							"note" : "O campo SH6.H6_OP é utilizado no Protheus PCP e o campo CYV.CYV_NRORPO é utilizado no Protheus SFC",
							"required": false,
							"available": true
						},
						{
							"product": "Logix",
							"field": "man_apo_mestre.ordem_producao",
							"required": false,
							"available": true
						},
						{
							"product": "Datasul ",
							"field": "rep-prod.nr-ord-prod",
							"required": false,
							"available": true
						}

					]
				},
				"Split": {
					"description": "Split",
					"type": "string",
					"maxLength": 10,
					"x-totvs": [
						{
							"product": "Protheus",
							"field": "SH6.H6_DESDOBR/CYV.CYV_IDATQO",
							"note" : "O campo SH6.H6_DESDOBR é utilizado no Protheus PCP e o campo CYV.CYV_IDATQO é utilizado no Protheus SFC",
							"required": false,
							"available": true
						},
						{
							"product": "Logix",
							"available": false
						},
						{
							"product": "Datasul ",
							"field": "split-operac.num-split-operac",
							"required": false,
							"available": true
						}

					]
				},
				"ExternalSplit": {
					"description": "Número externo do Split.",
					"type": "string",
					"maxLength": 10
				},
				"ActivityCode": {
					"description": "Código Operação",
					"type": "string",
					"maxLength": 10,
					"x-totvs": [
						{
							"product": "Protheus",
							"field": "SH6.H6_OPERAC/CYV.CYV_CDAT",
							"note" : "O campo SH6.H6_OPERAC é utilizado no Protheus PCP e o campo CYV.CYV_CDAT é utilizado no Protheus SFC",
							"required": false,
							"available": true
						},
						{
							"product": "Logix",
							"field":"man_apo_detalhe.operacao",
							"required": false,
							"available": true
						},
						{
							"product": "Datasul ",
							"field": "split-operac.num-operac-sfc",
							"required": false,
							"available": true
						}

					]
				},
				"ItemCode": {
					"description": "Código Item",
					"type": "string",
					"maxLength": 30,
					"x-totvs": [
						{
							"product": "Protheus",
							"field": "SH6.H6_PRODUTO/CYV.CYV_CDACRP",
							"note" : "O campo SH6.H6_PRODUTO é utilizado no Protheus PCP e o campo CYV.CYV_CDACRP é utilizado no Protheus SFC",
							"required": false,
							"available": true
						},
						{
							"product": "Logix",
							"field":"man_apo_mestre.item_produzido",
							"required": false,
							"available": true
						},
						{
							"product": "Datasul ",
							"field": "split-operac.it-codigo",
							"required": false,
							"available": true
						}

					]
				},
				"ItemDescription": {
					"description": "Descrição Item",
					"type": "string",
					"maxLength": 40
				},
				"ReportQuantity": {
					"description": "Quantidade Reportada",
					"type": "number",
					"multipleOf": 0.0001,
					"minimum": -99999999999.9999,
					"maximum": 99999999999.9999,
					"x-totvs": [
						{
							"product": "Protheus",
							"field": " ",
							"required": false,
							"available": false
						},
						{
							"product": "Logix",
							"field":" ",
							"required": false,
							"available": false
						},
						{
							"product": "Datasul ",
							"field": "rep-prod.qt-reporte",
							"required": false,
							"available": true
						}

					]
				},
				"ApprovedQuantity": {
					"description": "Quantidade Aprovada",
					"type": "number",
					"multipleOf": 0.0001,
					"minimum": -99999999999.9999,
					"maximum": 99999999999.9999,
					"x-totvs": [
						{
							"product": "Protheus",
							"field": "SH6.H6_QTDPROD/CYV.CYV_QTATAP",
							"note" : "O campo SH6.H6_QTDPROD é utilizado no Protheus PCP e o campo CYV.CYV_QTATAP é utilizado no Protheus SFC",
							"required": false,
							"available": true
						},
						{
							"product": "Logix",
							"field":"man_item_produzido.qtd_produzida",
							"required": false,
							"available": true
						},
						{
							"product": "Datasul ",
							"field": "rep-prod.qt-apr-cond ou rep-oper-ctrab.qtd-operac-aprov",
							"required": false,
							"available": true
						}

					]
				},
				"ScrapQuantity": {
					"description": "Quantidade Refugada",
					"type": "number",
					"multipleOf": 0.0001,
					"minimum": -99999999999.9999,
					"maximum": 99999999999.9999,
					"x-totvs": [
						{
							"product": "Protheus",
							"field": "SH6.H6_QTDPERD/CYV.CYV_QTATRF",
							"note" : "O campo SH6.H6_QTDPERD é utilizado no Protheus PCP e o campo CYV.CYV_QTATRF é utilizado no Protheus SFC",
							"required": false,
							"available": true
						},
						{
							"product": "Logix",
							"field":"man_item_produzido.qtd_produzida",
							"required": false,
							"available": true
						},
						{
							"product": "Datasul ",
							"field": "rep-prod.qt-refugo ou rep-oper-ctrab.qtd-operac-refgda",
							"required": false,
							"available": true
						}

					]
				},
				"ReworkQuantity": {
					"description": "Quantidade Retrabalhada",
					"type": "number",
					"multipleOf": 0.0001,
					"minimum": -99999999999.9999,
					"maximum": 99999999999.9999,
					"x-totvs": [
						{
							"product": "Protheus",
							"field": " ",
							"required": false,
							"available": false
						},
						{
							"product": "Logix",
							"field":" ",
							"required": false,
							"available": false
						},
						{
							"product": "Datasul ",
							"field": "rep-oper-ctrab.qtd-operac-retrab",
							"required": false,
							"available": true
						}

					]
				},
				"StartSetupDateTime": {
					"description": "Data/Hora Início Preparação",
					"type": "string",
					"format": "date-time",
					"x-totvs": [
						{
							"product": "Protheus",
							"field": "CYV_DTBGSU/CYV_HRBGSU",
							"note" : "O campo CYV_DTBGSU/CYV_HRBGSU é utilizado somente no Protheus SFC. Este campo não está disponível para o Protheus PCP.",
							"required": false,
							"available": true
						},
						{
							"product": "Logix",
							"field":" ",
							"required": false,
							"available": false
						},
						{
							"product": "Datasul ",
							"field": " ",
							"required": false,
							"available": false
						}

					]
				},
				"StartCentSetupTime": {
					"description": "Hora Centesimal Início Preparação",
					"type": "number",
					"multipleOf": 0.0001,
					"minimum": -999.9999,
					"maximum": 999.9999,
					"x-totvs": [
						{
							"product": "Protheus",
							"field": "SH6.H6_QTDPERD/CYV.CYV_QTATRF",
							"note" : "O campo SH6.H6_QTDPERD é utilizado no Protheus PCP e o campo CYV.CYV_QTATRF é utilizado no Protheus SFC",
							"required": false,
							"available": true
						},
						{
							"product": "Logix",
							"field":"man_item_produzido.qtd_produzida",
							"required": false,
							"available": true
						},
						{
							"product": "Datasul ",
							"field": "rep-prod.qt-refugo ou rep-oper-ctrab.qtd-operac-refgda",
							"required": false,
							"available": true
						}

					]
				},
				"EndSetupDateTime": {
					"description": "Data/Hora Fim Preparação",
					"type": "string",
					"format": "date-time",
					"x-totvs": [
						{
							"product": "Protheus",
							"field": "CYV_DTEDSU/CYV_HREDSU",
							"note" : "O campo CYV_DTEDSU/CYV_HREDSU é utilizado no Protheus SFC",
							"required": false,
							"available": true
						},
						{
							"product": "Logix",
							"field":" ",
							"required": false,
							"available": false
						},
						{
							"product": "Datasul ",
							"field": " ",
							"required": false,
							"available": false
						}

					]
				},
				"EndCentSetupTime": {  
					"description": "Hora Centesimal Fim Preparação",
					"type": "number",
					"multipleOf": 0.0001,
					"minimum": -999.9999,
					"maximum": 999.9999,
					"x-totvs": [
						{
							"product": "Protheus",
							"field": " ",
							"required": false,
							"available": false
						},
						{
							"product": "Logix",
							"field":" ",
							"required": false,
							"available": false
						},
						{
							"product": "Datasul ",
							"field": " ",
							"required": false,
							"available": false
						}

					]
				},
				"StartReportDateTime": {
					"description": "Data/Hora Início Reporte",
					"type": "string",
					"format": "date-time",
					"x-totvs": [
						{
							"product": "Protheus",
							"field": "SH6.H6_DATAINI + SH6.H6_HORAINI/CYV.CYV_DTRPBG+CYV.CYV_HRRPBG",
							"note" : "O campo SH6.H6_DATAINI + SH6.H6_HORAINI é utilizado no Protheus PCP e o campo CYV.CYV_DTRPBG+CYV.CYV_HRRPBG é utilizado no Protheus SFC",
							"required": false,
							"available": true
						},
						{
							"product": "Logix",
							"field":"man_tempo_producao.data_ini_producao + man_tempo_producao.hor_ini_producao",
							"required": false,
							"available": true
						},
						{
							"product": "Datasul ",
							"field": "rep-oper-ctrab.dat-inic-reporte + rep-oper-ctrab.qtd-segs-inic-reporte",
							"required": false,
							"available": true
						}

					]
				},
				"StartCentReportTime": {
					"description": "Hora Centesimal Início Reporte",
					"type": "number",
					"multipleOf": 0.0001,
					"minimum": -999.9999,
					"maximum": 999.9999
				},
				"EndReportDateTime": {
					"description": "Data/Hora Fim Reporte",
					"type": "string",
					"format": "date-time",
					"x-totvs": [
						{
							"product": "Protheus",
							"field": "SH6.H6_DATAFIN+SH6.H6_HORAFIN/CYV.CYV_DTRPED+CYV.CYV_HRRPED",
							"note" : "O campo SH6.H6_DATAFIN+SH6.H6_HORAFIN é utilizado no Protheus PCP e o campo CYV.CYV_DTRPED+CYV.CYV_HRRPED é utilizado no Protheus SFC",
							"required": false,
							"available": true
						},
						{
							"product": "Logix",
							"field":"man_tempo_producao.data_ini_producao + man_tempo_producao.hor_ini_producao",
							"required": false,
							"available": true
						},
						{
							"product": "Datasul ",
							"field": "rep-oper-ctrab.dat-fim-reporte + rep-oper-ctrab.qtd-segs-fim-reporte",
							"required": false,
							"available": true
						}

					]
				},
				"EndCentReportTime": {
					"description": "Hora Centesimal Fim Reporte",
					"type": "number",
					"multipleOf": 0.0001,
					"minimum": -999.9999,
					"maximum": 999.9999
				},
				"OpTimeDec": {
					"description": "Tempo Operação",
					"type": "number",
					"multipleOf": 0.01,
					"minimum": -9999999999.99,
					"maximum": 9999999999.99
				},
				"OpTimeInt": {
					"description": "Tempo Operação",
					"type": "integer",
					"minimum": -9999999999,
					"maximum": 9999999999,
					"format": "int32",
					"x-totvs": [
						{
							"product": "Protheus",
							"field": "CYV.CYV_QTTERP",
							"note" : "O campo CYV.CYV_QTTERP é utilizado no Protheus SFC. No Protheus PCP, este campo não está disponível",
							"required": false,
							"available": true
						},
						{
							"product": "Logix",
							"field":" ",
							"required": false,
							"available": false
						},
						{
							"product": "Datasul ",
							"field": " ",
							"required": false,
							"available": false
						}

					]
				},
				"ExtraTime": {
					"description": "Tempo Extra",
					"type": "integer",
					"minimum": -9999999999,
					"maximum": 9999999999,
					"format": "int32"
				},
				"StopTime": {
					"description": "Tempo Parada",
					"type": "integer",
					"minimum": -9999999999,
					"maximum": 9999999999,
					"format": "int32"
				},
				"MODTime": {
					"description": "Tempo Mão de Obra Direta",
					"type": "integer",
					"minimum": -9999999999,
					"maximum": 9999999999,
					"format": "int32"
				},
				"IsProductionControlReport": {
					"description": "Reporta Controle da Produção",
					"type": "boolean"
				},
				"CQLiberated": {
					"description": "Liberado Controle Qualidade",
					"type": "boolean"
				},
				"ReversedReport": {
					"description": "Reporte Estornado",
					"type": "boolean",
					"note":"O estorno ocorre quando o campo ReversedReport (Estorno do apontamento) possuir o conteúdo TRUE.",
					"x-totvs": [
						{
							"product": "Protheus",
							"field": " ",
							"note" : "TRUE/FALSE ",
							"required": false,
							"available": true
						},
						{
							"product": "Logix",
							"field":" ",
							"note" : "TRUE/FALSE ",
							"required": false,
							"available": true
						},
						{
							"product": "Datasul ",
							"field": " ",
							"note" : "TRUE/FALSE - Se for TRUE, então tem que observar campo IntegrationReport ",
							"required": false,
							"available": true
						}

					]
				},
				"ReversalDate": {
					"description": "Data Estorno",
					"type": "string",
					"format": "date",
					"x-totvs": [
						{
							"product": "Protheus",
							"field": "CYV.CYV_DTEO",
							"note" : "Somente no Protheus SFC esta tag é utilizada. ",
							"required": false,
							"available": true
						},
						{
							"product": "Logix",
							"field":" ",
							"required": false,
							"available": true
						},
						{
							"product": "Datasul ",
							"field": " ",
							"required": false,
							"available": true
						}

					]
				},
				"UpdateReport": {
					"description": "Atualiza Reporte",
					"type": "boolean"
				},
				"ProductionShiftCode": {
					"description": "Código Modelo Turno",
					"type": "string",
					"maxLength": 8,
					"x-totvs": [
						{
							"product": "Protheus",
							"field": "CYV.CYV_CDTN",
							"note" : "Somente no Protheus SFC esta tag é utilizada. ",
							"required": false,
							"available": true
						},
						{
							"product": "Logix",
							"field":" ",
							"required": false,
							"available": false
						},
						{
							"product": "Datasul ",
							"field": " ",
							"required": false,
							"available": false
						}

					]
				},
				"ProductionShiftDescription": {
					"description": "Descrição Modelo Turno",
					"type": "string",
					"maxLength": 40,
					"x-totvs": [
						{
							"product": "Protheus",
							"field": "CYL.CYL_DSTN",
							"note" : "Somente no Protheus SFC esta tag é utilizada. ",
							"required": false,
							"available": true
						},
						{
							"product": "Logix",
							"field":" ",
							"required": false,
							"available": false
						},
						{
							"product": "Datasul ",
							"field": " ",
							"required": false,
							"available": false
						}

					]
				},
				"ProductionShiftNumber": {
					"description": "Número Turno",
					"type": "string",
					"maxLength": 5,
					"x-totvs": [
						{
							"product": "Protheus",
							"field": "CYV.CYV_NRTN",
							"note" : "Somente no Protheus SFC esta tag é utilizada. ",
							"required": false,
							"available": true
						},
						{
							"product": "Logix",
							"field":"man_tempo_producao.turno_producao",
							"required": false,
							"available": true
						},
						{
							"product": "Datasul ",
							"field": " ",
							"required": false,
							"available": false
						}

					]
				},
				"ReportDateTime": {
					"description": "Data/Hora Reporte",
					"type": "string",
					"format": "date-time",
					"x-totvs": [
						{
							"product": "Protheus",
							"field": "SH6.H6_DTAPONT/CYV.CYV_DTRP + CYV.CYV_HRRP",
							"note" : "O campo SH6.H6_DTAPONT é utilizado no Protheus PCP. O campo CYV.CYV_DTRP + CYV.CYV_HRRP é utilizado no Protheus FSC",
							"required": false,
							"available": true
						},
						{
							"product": "Logix",
							"field":"man_apo_mestre.data_apontamento",
							"required": false,
							"available": true
						},
						{
							"product": "Datasul ",
							"field": "rep-prod.data",
							"required": false,
							"available": true
						}

					]
				},
				"ReportCentlTime": {
					"description": "Hora Centesimal Reporte",
					"type": "number",
					"multipleOf": 0.0001,
					"minimum": -999.9999,
					"maximum": 999.9999
				},
				"DocumentCode": {
					"description": "Documento",
					"type": "string",
					"maxLength": 20,
					"x-totvs": [
						{
							"product": "Protheus",
							"field": "CYV.CYV_NRDO",
							"Note": "O campo CYV.CYV_NRDO é utilizado no Protheus SFC. No Protheus PCP, este campo não está disponível",
							"required": false,
							"available": false
						},
						{
							"product": "Logix",
							"field":" ",
							"required": false,
							"available": false
						},
						{
							"product": "Datasul ",
							"field": "rep-prod.nro-docto",
							"required": false,
							"available": true
						}

					]
				},
				"DocumentSeries": {
					"description": "Série Documento",
					"type": "string",
					"maxLength": 5,
					"x-totvs": [
						{
							"product": "Protheus",
							"field": "CYV.CYV_NRSR",
							"Note": "O campo CYV.CYV_NRSR é utilizado no Protheus SFC. No Protheus PCP, este campo não está disponível",
							"required": false,
							"available": true
						},
						{
							"product": "Logix",
							"field":" ",
							"required": false,
							"available": false
						},
						{
							"product": "Datasul ",
							"field": "rep-prod.serie-docto",
							"required": false,
							"available": true
						}

					]
				},
				"WarehouseCode": {
					"description": "Código Depósito",
					"type": "string",
					"maxLength": 10,
					"x-totvs": [
						{
							"product": "Protheus",
							"field": "SH6.H6_LOCAL/CYV.CYV_CDDP",
							"Note": "O campo SH6.H6_LOCAL é utilizado no Protheus PCP e o campo CYV.CYV_CDDP é utilizado no Protheus SFC",
							"required": false,
							"available": true
						},
						{
							"product": "Logix",
							"field":"man_item_produzido.local",
							"required": false,
							"available": true
						},
						{
							"product": "Datasul ",
							"field": "rep-prod.serie-docto",
							"required": false,
							"available": true
						}

					]
				},
				"LotCode": {
					"description": "Lote/Série",
					"type": "string",
					"maxLength": 20,
					"x-totvs": [
						{
							"product": "Protheus",
							"field": "SH6.H6_LOTECTL/CYV.CYV_CDLOSR",
							"Note": "O campo SH6.H6_LOTECTL é utilizado no Protheus PCP e o campo CYV.CYV_CDLOSR é utilizado no Protheus SFC",
							"required": false,
							"available": true
						},
						{
							"product": "Logix",
							"field":"man_item_produzido.lote_produzido/man_item_produzido.serie",
							"Note": "Para o lote será utilizado o campo man_item_produzido.lote_produzido e para serie será utilizado o campo man_item_produzido.serie",
							"required": false,
							"available": true
						},
						{
							"product": "Datasul ",
							"field": "rep-prod.lote-serie",
							"required": false,
							"available": true
						}

					]
				},
				"LotDueDate": {
					"description": "Data Validade Lote",
					"type": "string",
					"format": "date",
					"x-totvs": [
						{
							"product": "Protheus",
							"field": "SH6.H6_DTVALID/CYV.CYV_DTVDLO",
							"Note": "O campo SH6.H6_DTVALID é utilizado no Protheus PCP e o campo CYV.CYV_DTVDLO é utilizado no Protheus SFC",
							"required": false,
							"available": true
						},
						{
							"product": "Logix",
							"field":"man_item_produzido.dat_valid",
							"required": false,
							"available": true
						},
						{
							"product": "Datasul ",
							"field": "rep-prod.dt-vali-lote",
							"required": false,
							"available": true
						}

					]
				},
				"ReferenceCode": {
					"description": "Código Referência",
					"type": "string",
					"maxLength": 20
				},
				"LocationCode": {
					"description": "Localização",
					"type": "string",
					"maxLength": 20,
					"x-totvs": [
						{
							"product": "Protheus",
							"field": "CYV.CYV_CDLC",
							"Note": "O campo CYV.CYV_CDLC é utilizado no Protheus SFC. No Protheus PCP, este campo não está disponível",
							"required": false,
							"available": true
						},
						{
							"product": "Logix",
							"field":"man_item_produzido.endereco",
							"required": false,
							"available": true
						},
						{
							"product": "Datasul ",
							"field": "rep-prod.cod-localiz",
							"required": false,
							"available": true
						}

					]
				},
				"SingleOutflowLocation": {
					"description": "Local Saída Início",
					"type": "boolean"
				},
				"OutflowLocationCode": {
					"description": "Localização Saída",
					"type": "string",
					"maxLength": 20,
					"x-totvs": [
						{
							"product": "Protheus",
							"field": " ",
							"required": false,
							"available": false
						},
						{
							"product": "Logix",
							"field":" ",
							"required": false,
							"available": false
						},
						{
							"product": "Datasul ",
							"field": "rep-prod.cod-local-sai",
							"required": false,
							"available": true
						}

					]
				},
				"OutflowWarehouseCode": {
					"description": "Código Depósito Saída",
					"type": "string",
					"maxLength": 10,
					"x-totvs": [
						{
							"product": "Protheus",
							"field": " ",
							"required": false,
							"available": false
						},
						{
							"product": "Logix",
							"field":" ",
							"required": false,
							"available": false
						},
						{
							"product": "Datasul ",
							"field": "rep-prod.cod-depos-sai",
							"required": false,
							"available": true
						}

					]
				},
				"WasteWarehouseCode": {
					"description": "Código Depósito Refugo",
					"type": "string",
					"maxLength": 10
				},
				"WasteLocationCode": {
					"description": "Localização Refugo",
					"type": "string",
					"maxLength": 20
				},
				"ReportSequence": {
					"description": "Sequência Reporte",
					"type": "string",
					"maxLength": 20
				},
				"ListOfReversalAppointments": {
						"type": "array",
						"multipleOf": 0.0001,
						"items": {
							"type": "object",
							"properties": {							
								"IntegrationReport": {
									"description": "Reporte Integração",
									"type": "string",
									"maxLength": 10,
									"x-totvs": [
										{
											"product": "Protheus",
											"field": " ",
											"Note":"Registro a ser estornado",
											"required": false,
											"available": true
										},
										{
											"product": "Logix",
											"field":"man_apo_mestre.seq_reg_mestre",
											"required": false,
											"available": true
										},
										{
											"product": "Datasul ",
											"field": " ",
											"note": "Quando o apontamento for de quantidade zero(0), este valor será buscado no Datasul usando o nr. da ordem + sequência.",
											"required": false,
											"available": true
										}
				
									]
								},
								"ReversalType": {
									"description": "Tipo de reversão / 1 - Produção / 2 - Recusa",
									"type": "string",
									"enum": [
										"1",
										"2"
									]
								},
								"ReversalQuantity": {
									"description": "Quantidade revertida",
									"type": "number",
									"minimum": -999999999999999,
									"maximum": 999999999999999
								}
							}
						}
				},
				"ToolCode": {
					"description": "Código Ferramenta",
					"type": "string",
					"maxLength": 20
				},
				"ToolDescription": {
					"description": "Descrição Ferramenta",
					"type": "string",
					"maxLength": 40
				},
				"SetupCode": {
					"description": "Código Preparação",
					"type": "string",
					"maxLength": 10,
					"x-totvs": [
						{
							"product": "Protheus",
							"field": "CYV_CDSU",
							"Note":"O campo CYV_CDSU é utilizado no Protheus SFC. No Protheus PCP, este campo não está disponível",
							"required": false,
							"available": true
						},
						{
							"product": "Logix",
							"field":" ",
							"required": false,
							"available": false
						},
						{
							"product": "Datasul ",
							"field": " ",
							"required": false,
							"available": false
						}

					]
				},
				"SetupDescription": {
					"description": "Descrição Preparação",
					"type": "string",
					"maxLength": 40
				},
				"CounterStart": {
					"description": "Início Contador",
					"type": "integer",
					"minimum": -999999999,
					"maximum": 999999999,
					"format": "int32"
				},
				"FinalAccountant": {
					"description": "Contador Fim",
					"type": "integer",
					"minimum": -999999999,
					"maximum": 999999999,
					"format": "int32"
				},
				"CloseOperation": {
					"description": "Encerra Operação",
					"type": "boolean",
					"x-totvs": [
						{
							"product": "Protheus",
							"field": "SH6.H6_PT/CYV.CYV_LGEDRP",
							"Note":"O campo SH6.H6_PT é utilizado no Protheus PCP e o campo CYV.CYV_LGEDRP é utilizado no Protheus SFC",
							"required": false,
							"available": true
						},
						{
							"product": "Logix",
							"field":"ord_oper.ies_apontamento",
							"required": false,
							"available": true
						},
						{
							"product": "Datasul ",
							"field": "tt-param-reporte.l-msg-finaliza-split-operac",
							"required": false,
							"available": true
						}

					]
				},
				"ListOfWasteAppointments": {
					"type": "array",
					"multipleOf": 0.0001,
					"items": {
						"type": "object",
						"properties": {
							"ScrapProduct": {
								"description": "Código do Produto Refugado",
								"type": "string",
								"maxLength": 30,
								"x-totvs": [
									{
										"product": "Protheus",
										"field": "SBC.BC_PRODUTO",
										"required": false,
										"available": true
									},
									{
										"product": "Logix",
										"field":" ",
										"required": false,
										"available": false
									},
									{
										"product": "Datasul ",
										"field": " ",
										"required": false,
										"available": false
									}
			
								]
							},
							"WarehouseCode": {
								"description": "Código Depósito",
								"type": "string",
								"maxLength": 10,
								"x-totvs": [
									{
										"product": "Protheus",
										"field": "SBC.BC_LOCORIG",
										"required": false,
										"available": true
									},
									{
										"product": "Logix",
										"field":" ",
										"required": false,
										"available": false
									},
									{
										"product": "Datasul ",
										"field": " ",
										"required": false,
										"available": false
									}
			
								]
							},
							"AddressCode": {
								"description": "Endereço origem",
								"type": "string",
								"maxLength": 15,
								"x-totvs": [
									{
										"product": "Protheus",
										"field": "SBC.BC_LOCALIZ",
										"required": false,
										"available": true
									},
									{
										"product": "Logix",
										"field":" ",
										"required": false,
										"available": false
									},
									{
										"product": "Datasul ",
										"field": " ",
										"required": false,
										"available": false
									}
			
								]
							},
							"NumberSeries": {
								"description": "Número de série Origem",
								"type": "string",
								"maxLength": 20,
								"x-totvs": [
									{
										"product": "Protheus",
										"field": "SBC.BC_NUMSERI",
										"required": false,
										"available": true
									},
									{
										"product": "Logix",
										"field":" ",
										"required": false,
										"available": false
									},
									{
										"product": "Datasul ",
										"field": " ",
										"required": false,
										"available": false
									}
			
								]
							},
							"ScrapProductTo": {
								"description": "Código do Produto Refugado Destino",
								"type": "string",
								"maxLength": 30,
								"x-totvs": [
									{
										"product": "Protheus",
										"field": "SBC.BC_CODDEST",
										"required": false,
										"available": true
									},
									{
										"product": "Logix",
										"field":"man_item_produzido.item_produzido",
										"required": false,
										"available": true
									},
									{
										"product": "Datasul ",
										"field": "Este campo indica que deve ser criada uma OP de reaproveitamento e que a quantidade refugada (ScrapQuantity) não gerará movimento de refugo(REF) no Datasul.",
										"note": "DMCP0076 - Reaproveitamento Interna Troca Código - Integração TOTVS MES",
										"required": false,
										"available": true
									}
			
								]
							},
							"WarehouseCodeTo": {
								"description": "Código Depósito Destino",
								"type": "string",
								"maxLength": 10,
								"x-totvs": [
									{
										"product": "Protheus",
										"field": "SBC.BC_LOCAL",
										"required": false,
										"available": true
									},
									{
										"product": "Logix",
										"field":"man_item_produzido.item_produzido",
										"required": false,
										"available": false
									},
									{
										"product": "Datasul ",
										"field": "Caso preenchido, senão é utilizado o depósito do acabado no apontamento",
										"required": false,
										"available": true
									}
			
								]
							},
							"AddressCodeTo": {
								"description": "Endereço Destino",
								"type": "string",
								"maxLength": 15,
								"x-totvs": [
									{
										"product": "Protheus",
										"field": "SBC.BC_LOCDEST",
										"required": false,
										"available": true
									},
									{
										"product": "Logix",
										"field":" ",
										"required": false,
										"available": false
									},
									{
										"product": "Datasul ",
										"field": " ",
										"required": false,
										"available": false
									}
			
								]
							},
							"NumberSeriesTo": {
								"description": "Número de série Destino",
								"type": "string",
								"maxLength": 20,
								"x-totvs": [
									{
										"product": "Protheus",
										"field": "SBC.BC_NSEDEST",
										"required": false,
										"available": true
									},
									{
										"product": "Logix",
										"field":" ",
										"required": false,
										"available": false
									},
									{
										"product": "Datasul ",
										"field": " ",
										"required": false,
										"available": false
									}
			
								]
							},
							"ReportSequence": {
								"description": "Sequência Reporte",
								"type": "string",
								"maxLength": 20
							},
							"WasteCode": {
								"description": "Código Refugo",
								"type": "string",
								"maxLength": 8,
								"x-totvs": [
									{
										"product": "Protheus",
										"field": "SBC.BC_MOTIVO/CY0.CY0_CDRF",
										"note":"O campo SBC.BC_MOTIVO é utilizado no Protheus PCP e o campo CY0.CY0_CDRF é utilizado no Protheus SFC",
										"required": false,
										"available": true
									},
									{
										"product": "Logix",
										"field":"man_def_producao.motivo_defeito",
										"required": false,
										"available": true
									},
									{
										"product": "Datasul ",
										"field": "tt-ref.cod-motiv-refugo",
										"required": false,
										"available": true
									}
			
								]
							},
							"WasteDescription": {
								"description": "Descrição Refugo",
								"type": "string",
								"maxLength": 40,
								"x-totvs": [
									{
										"product": "Protheus",
										"field": "SBC.BC_DESCRI/CY0.CY0_DSRF",
										"note":"O campo SBC.BC_DESCRI é utilizado no Protheus PCP e o campo CY0.CY0_DSRF é utilizado no Protheus SFC",
										"required": false,
										"available": true
									},
									{
										"product": "Logix",
										"field":"defeito.den_defeito",
										"required": false,
										"available": true
									},
									{
										"product": "Datasul ",
										"field": " ",
										"required": false,
										"available": false
									}
			
								]
							},
							"ScrapQuantity": {
								"description": "Quantidade Refugada", 
								"type": "number",
								"minimum": -999999999999999,
								"maximum": 999999999999999,
								"x-totvs": [
									{
										"product": "Protheus",
										"field": "SBC.BC_QUANT/CY0.CY0_QTRF",
										"required": false,
										"available": true
									},
									{
										"product": "Logix",
										"field":"man_def_producao.qtd_defeito_real",
										"required": false,
										"available": true
									},
									{
										"product": "Datasul ",
										"field": "tt-ref.qtd-operac-refgda",
										"required": false,
										"available": true
									}
			
								]
							},
							"ReworkQuantity": {
								"description": "Quantidade Retrabalhada",
								"type": "number",
								"minimum": -999999999999999,
								"maximum": 999999999999999,
								"x-totvs": [
									{
										"product": "Protheus",
										"field": " ",
										"required": false,
										"available": false
									},
									{
										"product": "Logix",
										"field":" ",
										"required": false,
										"available": false
									},
									{
										"product": "Datasul ",
										"field": "tt-ret.qtd-operac-retrab",
										"required": false,
										"available": true
									}
			
								]
							},
							"LotCode": {
								"description": "Número do lote",
								"type": "string",
								"maxLength": 10,
								"x-totvs": [
									{
										"product": "Protheus",
										"field": "SBC.BC_LOTECTL",
										"required": false,
										"available": true
									},
									{
										"product": "Logix",
										"field":" ",
										"required": false,
										"available": false
									},
									{
										"product": "Datasul ",
										"field": "Caso seja preenchido, e o item informado em ScrapProductTo use o conceito de lote, será usado para o apontamento da produção.",
										"required": false,
										"available": true
									}
			
								]
							},
							"SubLotCode": {
								"description": "Sublote",
								"type": "string",
								"maxLength": 20,
								"x-totvs": [
									{
										"product": "Protheus",
										"field": "SBC.BC_NUMLOTE",
										"required": false,
										"available": true
									},
									{
										"product": "Logix",
										"field":" ",
										"required": false,
										"available": false
									},
									{
										"product": "Datasul ",
										"field": " ",
										"required": false,
										"available": false
									}
			
								]
							},
							"LotDueDate": {
								"description": "Data de validade do lote",
								"type": "string",
								"format": "date",
								"x-totvs": [
									{
										"product": "Protheus",
										"field": "SBC.BC_DTVALID",
										"required": false,
										"available": true
									},
									{
										"product": "Logix",
										"field":" ",
										"required": false,
										"available": false
									},
									{
										"product": "Datasul ",
										"field": "Caso o lote seja novo, então, o campo LotDueDate será também aproveitado",
										"required": false,
										"available": true
									}
			
								]
							},
							"CostCenterCode": {
								"description": "Centro de custo",
								"type": "string",
								"maxLength": 10,
								"x-totvs": [
									{
										"product": "Protheus",
										"field": "SBC.BC_CC",
										"required": false,
										"available": true
									},
									{
										"product": "Logix",
										"field":" ",
										"required": false,
										"available": false
									},
									{
										"product": "Datasul ",
										"field": " ",
										"required": false,
										"available": false
									}
			
								]
							}
						}
					}
				},
				"ListOfResourceAppointments": {
					"type": "array",
					"multipleOf": 0.0001,
					"items": {
						"type": "object",
						"properties": {
							"ReportSequence": {
								"description": "Sequência Reporte",
								"type": "string",
								"maxLength": 20
							},
							"OperatorID": {
								"description": "ID Operador",
								"type": "string",
								"maxLength": 10
							},
							"OperatorCode": {
								"description": "Código Operador",
								"type": "string",
								"maxLength": 20,
								"x-totvs": [
									{
										"product": "Protheus",
										"field": "CYW.CYW_CDOE",
										"required": false,
										"available": true
									},
									{
										"product": "Logix",
										"field":"man_apo_detalhe.operador",
										"required": false,
										"available": true
									},
									{
										"product": "Datasul ",
										"field": "tt-apont-mob.cd-mob-dir = π operador.cd-mob-dir  (? operador.cod-operador = OperatorCode (operador)).",
										"nota":"Caso não informado o código do Operador, será usado o mesmo código de mão de obra da operação da ordem (LaborCode)",
										"required": false,
										"available": true
									}
			
								]
							},
							"OperatorName": {
								"description": "Nome Operador",
								"type": "string",
								"maxLength": 40
							},
							"ProductionTeamCode": {
								"description": "Código Equipe Produção",
								"type": "string",
								"maxLength": 20
							},
							"StartDateTime": {
								"description": "Data/Hora Início",
								"type": "string",
								"format": "date-time",
								"x-totvs": [
									{
										"product": "Protheus",
										"field": "CYW.CYW_DTBGRP+CYW.CYW_HRBGRP",
										"required": false,
										"available": true
									},
									{
										"product": "Logix",
										"field":" ",
										"required": false,
										"available": false
									},
									{
										"product": "Datasul ",
										"field": "tt-apont-mob.hora-ini e tt-apont-mob.min-ini ",
										"nota":"Se informado StartDateTime então tt-apont-mob.tipo-relogio =  1; tt-apont-mob.hora-ini = HH; tt-apont-mob.min-ini = MM; tt-apont-mob.minutos-report =  EndDateTime - StartDateTime",
										"required": false,
										"available": true
									}
			
								]
							},
							"StartCentTime": {
								"description": "Hora Centesimal Início",
								"type": "number",
								"minimum": -9999999,
								"maximum": 9999999
							},
							"EndDateTime": {
								"description": "Data/Hora Fim",
								"type": "string",
								"format": "date-time",
								"x-totvs": [
									{
										"product": "Protheus",
										"field": "CYW.CYW_DTBGRP+CYW.CYW_HRBGRP",
										"required": false,
										"available": true
									},
									{
										"product": "Logix",
										"field":" ",
										"required": false,
										"available": false
									},
									{
										"product": "Datasul ",
										"field": "tt-apont-mob.hora-fim e tt-apont-mob.min-fim",
										"nota":"Se informado EndDateTime então tt-apont-mob.hora-fim = HH; tt-apont-mob.min-fim = MM; tt-apont-mob.minutos-report =  EndDateTime - StartDateTime",
										"required": false,
										"available": true
									}
			
								]
							},
							"EndCentTime": {
								"description": "Hora Centesimal Fim",
								"type": "number",
								"minimum": -9999999,
								"maximum": 9999999
							},
							"MOBTime": {
								"description": "Tempo Mão de Obra Direta",
								"type": "integer",
								"minimum": -9999999999,
								"maximum": 9999999999,
								"format": "int32",
								"x-totvs": [
									{
										"product": "Protheus",
										"field": "CYW.CYW_QTTEOE",
										"note": "O campo CYW.CYW_QTTEOE é utilizado no Protheus SFC. No Protheus PCP, este campo não está disponível",
										"required": false,
										"available": true
									},
									{
										"product": "Logix",
										"field":" ",
										"required": false,
										"available": false
									},
									{
										"product": "Datasul ",
										"field": " ",
										"required": false,
										"available": false
									}
			
								]
							},
							"ExtraTime": {
								"description": "Tempo Extra",
								"type": "integer",
								"minimum": -9999999999,
								"maximum": 9999999999,
								"format": "int32",
								"x-totvs": [
									{
										"product": "Protheus",
										"field": "CYW.CYW_QTTEEX",
										"note": "O campo CYW.CYW_QTTEEX é utilizado no Protheus SFC. No Protheus PCP, este campo não está disponível",
										"required": false,
										"available": true
									},
									{
										"product": "Logix",
										"field":" ",
										"required": false,
										"available": false
									},
									{
										"product": "Datasul ",
										"field": " ",
										"required": false,
										"available": false
									}
			
								]
							},
							"UtilTime": {
								"description": "Tempo Útil",
								"type": "integer",
								"minimum": -9999999999,
								"maximum": 9999999999,
								"format": "int32",
								"x-totvs": [
									{
										"product": "Protheus",
										"field": "CYW.CYW_QTTEUT",
										"note": "O campo CYW.CYW_QTTEUT é utilizado no Protheus SFC. No Protheus PCP, este campo não está disponível",
										"required": false,
										"available": true
									},
									{
										"product": "Logix",
										"field":" ",
										"required": false,
										"available": false
									},
									{
										"product": "Datasul ",
										"field": " ",
										"required": false,
										"available": false
									}
			
								]
							},
							"ProductionShiftCode": {
								"description": "Código Modelo Turno",
								"type": "string",
								"maxLength": 8,
								"x-totvs": [
									{
										"product": "Protheus",
										"field": "CYW.CYW_CDTN",
										"note": "O campo CYW.CYW_CDTN é utilizado no Protheus SFC. No Protheus PCP, este campo não está disponível",
										"required": false,
										"available": true
									},
									{
										"product": "Logix",
										"field":" ",
										"required": false,
										"available": false
									},
									{
										"product": "Datasul ",
										"field": " ",
										"required": false,
										"available": false
									}
			
								]
							},
							"ProductionShiftNumber": {
								"description": "Número Turno",
								"type": "string",
								"maxLength": 5,
								"x-totvs": [
									{
										"product": "Protheus",
										"field": "CYW.CYW_NRTN",
										"note": "O campo CYW.CYW_NRTN é utilizado no Protheus SFC. No Protheus PCP, este campo não está disponível",
										"required": false,
										"available": true
									},
									{
										"product": "Logix",
										"field":" ",
										"required": false,
										"available": false
									},
									{
										"product": "Datasul ",
										"field": " ",
										"required": false,
										"available": false
									}
			
								]
							}
						}
					}
				},
				"ListOfSupplyOrders": {
					"type": "array",
					"multipleOf": 0.0001,
					"items": {
						"type": "object",
						"properties": {
							"ReportSequence": {
								"description": "Sequência Reporte",
								"type": "string",
								"maxLength": 20
							},
							"ProductionOrderNumber": {
								"description": "Número Ordem Produção",
								"type": "string",
								"maxLength": 20,
								"x-totvs": [
									{
										"product": "Protheus",
										"field": "SD3.D3_OP/CZP.CZP_NRORPO",
										"note": "O campo SD3.D3_OP é utilizado no Protheus PCP e o campo CZP.CZP_NRORPO é utilizado no Protheus SFC",
										"required": false,
										"available": true
									},
									{
										"product": "Logix",
										"field":"man_apo_mestre.ordem_producao",
										"required": false,
										"available": true
									},
									{
										"product": "Datasul ",
										"field": "tt-res-neg.nr-ord-produ",
										"required": false,
										"available": true
									}
			
								]
							},
							"MaterialCode": {
								"description": "Código Item Reserva",
								"type": "string",
								"maxLength": 30,
								"x-totvs": [
									{
										"product": "Protheus",
										"field": "SD3.D3_COD/CZP.CZP_CDMT",
										"note": "O campo SD3.D3_COD é utilizado no Protheus PCP e o campo CZP.CZP_CDMT é utilizado no Protheus SFC",
										"required": false,
										"available": true
									},
									{
										"product": "Logix",
										"field":"man_comp_consumido.item_componente",
										"required": false,
										"available": true
									},
									{
										"product": "Datasul ",
										"field": "tt-res-neg.it-codigo",
										"required": false,
										"available": true
									}
			
								]
							},
							"MaterialDescription": {
								"description": "Descrição Item Reserva",
								"type": "string",
								"maxLength": 40
							},
							"ReferenceCode": {
								"description": "Código Referência",
								"type": "string",
								"maxLength": 20
							},
							"UsedQuantity": {
								"description": "Quantidade Utilizada",
								"type": "number",
								"minimum": -99999999999999,
								"maximum": 99999999999999,
								"x-totvs": [
									{
										"product": "Protheus",
										"field": "SD3.D3_QUANT/CZP.CZP_QTRPPO",
										"note": "O campo SD3.D3_QUANT é utilizado no Protheus PCP e o campo CZP.CZP_QTRPPO é utilizado no Protheus SFC",
										"required": false,
										"available": true
									},
									{
										"product": "Logix",
										"field":"man_comp_consumido.qtd_baixa_real",
										"required": false,
										"available": true
									},
									{
										"product": "Datasul ",
										"field": "tt-res-neg.quantidade",
										"required": false,
										"available": true
									}
			
								]
							},
							"ApprovedQuantity": {
								"description": "Quantidade Aprovada",
								"type": "number",
								"minimum": -999999999999999,
								"maximum": 999999999999999
							},
							"UnitOfMeasureCode": {
								"description": "Unidade Medida",
								"type": "string",
								"maxLength": 6
							},
							"FatherItemCode": {
								"description": "Código Item Pai",
								"type": "string",
								"maxLength": 30
							},
							"FatherItemDescription": {
								"description": "Descrição Item Pai",
								"type": "string",
								"maxLength": 40
							},
							"WarehouseCode": {
								"description": "Código Depósito",
								"type": "string",
								"maxLength": 10,
								"x-totvs": [
									{
										"product": "Protheus",
										"field": "SD3.D3_LOCAL/CZP.CZP_CDDP",
										"note": "O campo SD3.D3_LOCAL é utilizado no Protheus PCP e o campo CZP.CZP_CDDP é utilizado no Protheus SFC",
										"required": false,
										"available": true
									},
									{
										"product": "Logix",
										"field":"man_comp_consumido.local_estoque",
										"required": false,
										"available": true
									},
									{
										"product": "Datasul ",
										"field": "tt-res-neg.cod-depos",
										"required": false,
										"available": true
									}
			
								]
							},
							"LocationCode": {
								"description": "Localização",
								"type": "string",
								"maxLength": 20,
								"x-totvs": [
									{
										"product": "Protheus",
										"field": "SD3.D3_LOCALIZ/CZP.CZP_CDLC",
										"note": "O campo SD3.D3_LOCALIZ é utilizado no Protheus PCP e o campo CZP.CZP_CDLC é utilizado no Protheus SFC",
										"required": false,
										"available": true
									},
									{
										"product": "Logix",
										"field":"man_comp_consumido.endereco",
										"required": false,
										"available": true
									},
									{
										"product": "Datasul ",
										"field": "tt-res-neg.cod-localiz",
										"required": false,
										"available": true
									}
			
								]
							},
							"LotCode": {
								"description": "Lote/Série",
								"type": "string",
								"maxLength": 20,
								"x-totvs": [
									{
										"product": "Protheus",
										"field": "SD3.D3_LOCALIZ/CZP.CZP_CDLC",
										"note": "O campo SD3.D3_LOCALIZ é utilizado no Protheus PCP e o campo CZP.CZP_CDLC é utilizado no Protheus SFC",
										"required": false,
										"available": true
									},
									{
										"product": "Logix",
										"field":"man_comp_consumido.lote_componente/man_comp_consumido.serie",
										"note":"O campo man_comp_consumido.lote_componente será utilizado para os itens com controle de lote e o campo man_comp_consumido.serie será utilizado para os itens com controle de serie",
										"required": false,
										"available": true
									},
									{
										"product": "Datasul ",
										"field": "tt-res-neg.lote-serie",
										"required": false,
										"available": true
									}
			
								]
							},
							"ActivityCode": {
								"description": "Código Operação",
								"type": "string",
								"maxLength": 10,
								"x-totvs": [
									{
										"product": "Protheus",
										"field": "CZP.CZP_CDAT",
										"note": "O campo CZP.CZP_CDAT é utilizado no Protheus SFC. No Protheus PCP, este campo não está disponível",
										"required": false,
										"available": true
									},
									{
										"product": "Logix",
										"field":" ",
										"required": false,
										"available": false
									},
									{
										"product": "Datasul ",
										"field": "tt-reservas.op-codigo",
										"required": false,
										"available": true
									}
			
								]
							},
							"ScriptCode": {
								"description": "Código Roteiro",
								"type": "string",
								"maxLength": 20,
								"x-totvs": [
									{
										"product": "Protheus",
										"field": "CZP.CZP_CDRT",
										"note": "O campo CZP.CZP_CDRT é utilizado no Protheus SFC. No Protheus PCP, este campo não está disponível",
										"required": false,
										"available": true
									},
									{
										"product": "Logix",
										"field":" ",
										"required": false,
										"available": false
									},
									{
										"product": "Datasul ",
										"field": " ",
										"required": false,
										"available": false
									}
			
								]
							},
							"SiteCode": {
								"description": "Código Estabelecimento",
								"type": "string",
								"maxLength": 5
							},
							"MaterialDate": {
								"description": "Data Reserva",
								"type": "string",
								"format": "date"
							},
							"MaterialQuantity": {
								"description": "Quantidade Reserva",
								"type": "number",
								"minimum": -99999999999999,
								"maximum": 99999999999999
							},
							"StatusType": {
								"description": "Estado / 1 - Ativo / 2 - Inativo",
								"type": "string",
								"enum": [
									"1",
									"2"
								]
							},
							"OrderProcess": {
								"description": "Processo Ordem",
								"type": "string",
								"maxLength": 20
							},
							"ReferenceOrderNumber": {
								"description": "Número Ordem Referência",
								"type": "string",
								"maxLength": 20
							},
							"MaterialID": {
								"description": "ID Reserva",
								"type": "string",
								"maxLength": 10
							}
						}
					}
				},
				"ListOfReportToolActivities": {
					"type": "array",
					"items": {
						"type": "object",
						"properties": {
							"ReportSequence": {
								"description": "Sequência Reporte",
								"type": "string",
								"maxLength": 20
							},
							"ToolCode": {
								"description": "Código Ferramenta",
								"type": "string",
								"maxLength": 20,
								"x-totvs": [
									{
										"product": "Protheus",
										"field": "CZ0.CZ0_IDFE",
										"note": "O campo CZ0.CZ0_IDFE é utilizado no Protheus SFC. No Protheus PCP, este campo não está disponível",
										"required": false,
										"available": true
									},
									{
										"product": "Logix",
										"field":" ",
										"required": false,
										"available": false
									},
									{
										"product": "Datasul ",
										"field": "cod-ferr-prod",
										"required": false,
										"available": true
									}
			
								]
							},
							"ToolDescription": {
								"description": "Descrição Ferramenta",
								"type": "string",
								"maxLength": 40
							},
							"OperationUnitTime": {
								"description": "Tempo Unidade Operação",
								"type": "integer",
								"minimum": -9999999999,
								"maximum": 9999999999,
								"format": "int32"
							}
						}
					}
				},
				"ListOfReportOverheads": {
					"type": "array",
					"multipleOf": 0.0001,
					"items": {
						"type": "object",
						"properties": {
							"ReportSequence": {
								"description": "Sequência Reporte",
								"type": "string",
								"maxLength": 20
							},
							"WorkCenterCode": {
								"description": "Código Centro Trabalho",
								"type": "string",
								"maxLength": 10
							},
							"WorkCenterDescription": {
								"description": "Descrição Centro Trabalho",
								"type": "string",
								"maxLength": 40
							},
							"GGFTimeInt": {
								"description": "Tempo Gastos Gerais de Fabricação",
								"type": "integer",
								"minimum": -9999999999,
								"maximum": 9999999999,
								"format": "int32"
							},
							"GGFTimeDec": {
								"description": "Tempo Gastos Gerais de Fabricação",
								"type": "number",
								"minimum": -9999999999,
								"maximum": 9999999999
							}
						}
					}
				},
				"CompanyId": {
					"description": "Empresa",
					"type": "string",
					"x-totvs": [
						{
							"product": "PIMS",
							"field": "MSIEMPRE.CD_INT_ERP",
							"required": true,
							"type": "varchar",
							"length": "10",
							"note": "Código da Empresa",
							"available": true,
							"canUpdate": false
						}
					]
				},
				"BranchId": {
					"description": "Filial",
					"type": "string",
					"x-totvs": [
						{
							"product": "PIMS",
							"field": "MSIEMPRE.CD_INT_ERP",
							"required": true,
							"type": "varchar",
							"length": "10",
							"note": "Código da Filial",
							"available": true,
							"canUpdate": false
						}
					]
				},
				"CostCenterCode": {
					"description": "Código do Centro de Custo",
					"type": "string",
					"x-totvs": [
						{
							"product": "PIMS",
							"field": "PROCENCUSTO.CD_INT_ERP",
							"required": false,
							"type": "char",
							"length": "20",
							"note": "Código do Centro de Custo",
							"available": true,
							"canUpdate": false
						}
					]
				},
				"SubCostCenterCode": {
					"description": "Subcentro de Custo",
					"type": "string",
					"x-totvs": [
						{
							"product": "PIMS",
							"field": "PROSUBCENCUSTO.CD_INT_ERP",
							"required": false,
							"type": "char",
							"length": "9",
							"note": "Código do Subcentro de Custos",
							"available": true,
							"canUpdate": false
						}
					]
				},
				"MovementType": {
					"description": "Tipo de Movimento / 1 - Entrada / 2 - Saida / 3 - Outros",
					"type": "string",
					"enum": [
						"1",
						"2",
						"3"
					],
					"x-totvs": [
						{
							"product": "PIMS",
							"field": "MOV_SITUACAO",
							"required": true,
							"type": "Number",
							"length": "1",
							"note": "Tipo de Movimento",
							"available": true,
							"canUpdate": false
						}
					]
				}
			}
		},
		"ReturnContentType": {
			"type": "object",
			"properties": {
				"ListOfInternalId": {
					"type": "array",
					"items": {
						"$ref": "https://raw.githubusercontent.com/totvs/ttalk-standard-message/master/jsonschema/schemas/types/ListOfInternalId_1_000.json#/definitions/ListOfInternalIdType",
						"type": "object"
					}
				}
			}
		}
	}
}