{
	"openapi": "3.0.1",
	"servers": [
		{
			"description": "API para produtos TOTVS",
			"url": "http://{domain}:{port}/api/hcg/v1",
			"variables": {
				"domain": {
					"default": "localhost"
				},
				"port": {
					"default": "8051"
				}
			}
		}
	],
	"info": {
		"description": "API para a entidade MedicalSpecialty para produtos TOTVS",
		"version": "1.000",
		"title": "MedicalSpecialty",
		"contact": {
			"name": "T-Talk",
			"url": "api.totvs.com.br",
			"email": "comiteintegracao@totvs.com.br"
		},
		"x-totvs": {
			"messageDocumentation": {
				"name": "MedicalSpecialty",
				"description": "Tabela de Especialidades Medicas",
				"segment": "Saúde"
			},
            "productInformation": [
                {
                    "product": "RM",
                    "contact": "TOTVS.SAUDE.SQUAD.GHASSIST@totvs.com.br",
                    "description": "Consulta de Especialidades Medicas",
                    "adapter": "",
                    "helpUrl": ""
                }
            ]
		}
	},
	"paths": {
		"/medicalSpecialties/{code}": {
			"get": {
				"tags": [
					"MedicalSpecialty"
				],
				"summary": "Retorna dados de tabela de especialidades medicas",
				"x-totvs": {
                    "productInformation": [
                        {
                            "product": "RM",
                            "available": true,
                            "note": "Este verbo esta disponivel com todos parametros",
                            "minimalVersion": "12.1.26"
                        }
                    ]
				},
				"description": "Retorna dados de tabela de especialidades medicas",
				"operationId": "getMedicalSpecialtyById",
				"parameters": [
                    {
                        "in": "path",
                        "name": "code",
                        "description": "Código",
                        "required": true,
                        "schema": {
                            "type": "string"
                        }
                    }
				],
				"responses": {
					"200": {
						"description": "Operação executada com sucesso",
						"content": {
							"application/json": {
								"schema": {
									"$ref": "https://raw.githubusercontent.com/totvs/ttalk-standard-message/master/jsonschema/schemas/MedicalSpecialty_1_000.json#/definitions/MedicalSpecialty"
								}
							}
						}
					},
					"500": {
						"description": "Erro na execução da operação",
						"content": {
							"application/json": {
								"schema": {
									"$ref": "https://raw.githubusercontent.com/totvs/ttalk-standard-message/master/jsonschema/apis/types/totvsApiTypesBase.json#/definitions/ErrorModel"
								}
							}
						}
					}
				}
			}
		},
		"/medicalSpecialties": {
			"get": {
				"tags": [
					"MedicalSpecialty"
				],
				"summary": "Busca dados de tabela de especialidades medicas existentes",
				"x-totvs": {
                    "productInformation": [
                        {
                            "product": "RM",
                            "available": true,
                            "note": "Este verbo esta disponivel com todos parametros",
                            "minimalVersion": "12.1.26"
                        }
                    ]
				},
				"description": "Busca dados de tabela de especialidades medicas existentes",
				"operationId": "getMedicalSpecialtyByFilter",
				"parameters": [
					{
						"$ref": "https://raw.githubusercontent.com/totvs/ttalk-standard-message/master/jsonschema/apis/types/totvsApiTypesBase.json#/parameters/Order"
					},
					{
						"$ref": "https://raw.githubusercontent.com/totvs/ttalk-standard-message/master/jsonschema/apis/types/totvsApiTypesBase.json#/parameters/Page"
					},
					{
						"$ref": "https://raw.githubusercontent.com/totvs/ttalk-standard-message/master/jsonschema/apis/types/totvsApiTypesBase.json#/parameters/PageSize"
					},
					{
						"$ref": "https://raw.githubusercontent.com/totvs/ttalk-standard-message/master/jsonschema/apis/types/totvsApiTypesBase.json#/parameters/Fields"
					}
				],
				"responses": {
					"200": {
						"description": "Operação executada com sucesso",
						"content": {
							"application/json": {
								"schema": {
									"$ref": "https://raw.githubusercontent.com/totvs/ttalk-standard-message/master/jsonschema/schemas/MedicalSpecialty_1_000.json#/definitions/PagedMedicalSpecialty"
								}
							}
						},
					"500": {
						"description": "Erro na execução da operação",
						"content": {
							"application/json": {
								"schema": {
									"$ref": "https://raw.githubusercontent.com/totvs/ttalk-standard-message/master/jsonschema/apis/types/totvsApiTypesBase.json#/definitions/ErrorModel"
								}
							}
						}
					},
					"500": {
						"description": "Erro na execução da operação",
						"content": {
							"application/json": {
								"schema": {
									"$ref": "https://raw.githubusercontent.com/totvs/ttalk-standard-message/master/jsonschema/apis/types/totvsApiTypesBase.json#/definitions/ErrorModel"
								}
							}
						}
					}
				}
			}
		}
	}
}